tests/__init__.py
university/__init__.py
university/__main__.py
university/hooking/__init__.py
university/hooking/ante_build_hook.py
university/hooking/ante_release_hook.py
university/hooking/post_build_hook.py
university/hooking/post_release_hook.py
university/pyrustic_data/hooking.json
university/pyrustic_data/hubstore.json
university/pyrustic_data/release_info.json
university-0.0.1.dist-info/LICENSE
university-0.0.1.dist-info/METADATA
university-0.0.1.dist-info/WHEEL
university-0.0.1.dist-info/entry_points.txt
university-0.0.1.dist-info/top_level.txt
university-0.0.1.dist-info/RECORD
