Metadata-Version: 2.1
Name: university
Version: 0.0.1
Summary: Secret
Home-page: https://github.com/pyrustic/university
Author: Pyrustic Evangelist
Author-email: pyrustic@protonmail.com
Maintainer: Pyrustic Evangelist
Maintainer-email: pyrustic@protonmail.com
License: MIT
Keywords: desktop-application
Platform: UNKNOWN
Classifier: Programming Language :: Python :: 3
Classifier: License :: OSI Approved :: MIT License
Classifier: Operating System :: OS Independent
Requires-Python: >=3.5
